apitest/__init__.py
apitest/api_usage_test.py
jcollections/Iterable.py
jcollections/Predicate.py
jcollections/__init__.py
jcollections/abstractqueue.py
jcollections/arraydeque.py
jcollections/arraylist.py
jcollections/collection.py
jcollections/hashmap.py
jcollections/hashset.py
jcollections/hashtable.py
jcollections/linkedhashmap.py
jcollections/linkedhashset.py
jcollections/linkedlist.py
jcollections/list.py
jcollections/map.py
jcollections/mapentry.py
jcollections/priorityqueue.py
jcollections/queue.py
jcollections/set.py
jcollections/sortedmap.py
jcollections/sortedset.py
jcollections/stack.py
jcollections/treemap.py
jcollections/treeset.py
jcollections/vector.py
jstring/__init__.py
jstring/character.py
jstring/string.py
jstring/stringbuffer.py
jstring/stringbuilder.py
tests/__init__.py
tests/test_character.py
tests/test_charsequence.py
tests/test_string.py
tests/test_stringbuffer.py
tests/test_stringbuilder.py
pyjcore-1.0.1.dist-info/LICENSE.txt
pyjcore-1.0.1.dist-info/METADATA
pyjcore-1.0.1.dist-info/WHEEL
pyjcore-1.0.1.dist-info/top_level.txt
pyjcore-1.0.1.dist-info/RECORD
