Metadata-Version: 2.1
Name: pyjcore
Version: 1.0.1
Summary: A Python package that mimics Core Java collection classes
Home-page: https://github.com/Sariya-Ansari/pyjcore.git
Author: Sariya Ansari
Author-email: 
Classifier: Programming Language :: Python :: 3
Classifier: License :: OSI Approved :: MIT License
Classifier: Operating System :: OS Independent
Requires-Python: >=3.6
License-File: LICENSE.txt
